{
    "fluentMethods": true,
    "relationships": [
        {
            "relationshipType": "one-to-one",
            "relationshipName": "unit",
            "otherEntityName": "unit",
            "ownerSide": false,
            "otherEntityRelationshipName": "ratingMethod"
        }
    ],
    "fields": [
        {
            "fieldName": "ratingMethod",
            "fieldType": "byte[]",
            "fieldTypeBlobContent": "text"
        }
    ],
    "changelogDate": "20180425120538",
    "entityTableName": "rating_method",
    "dto": "no",
    "pagination": "no",
    "service": "no",
    "jpaMetamodelFiltering": false
}